// Header guards omitted on purpose
#ifndef GEEVM_HANDLE_OPCODE
#error "GEEVM_HANDLE_OPCODE must be defined before including this file"
#else
  // Constants
  //==-------------------------------------------------------------------==//
  GEEVM_HANDLE_OPCODE(NOP, 0x00)
  GEEVM_HANDLE_OPCODE(ACONST_NULL, 0x01)
  GEEVM_HANDLE_OPCODE(ICONST_M1, 0x02)
  GEEVM_HANDLE_OPCODE(ICONST_0, 0x03)
  GEEVM_HANDLE_OPCODE(ICONST_1, 0x04)
  GEEVM_HANDLE_OPCODE(ICONST_2, 0x05)
  GEEVM_HANDLE_OPCODE(ICONST_3, 0x06)
  GEEVM_HANDLE_OPCODE(ICONST_4, 0x07)
  GEEVM_HANDLE_OPCODE(ICONST_5, 0x08)
  GEEVM_HANDLE_OPCODE(LCONST_0, 0x09)
  GEEVM_HANDLE_OPCODE(LCONST_1, 0x0a)
  GEEVM_HANDLE_OPCODE(FCONST_0, 0x0b)
  GEEVM_HANDLE_OPCODE(FCONST_1, 0x0c)
  GEEVM_HANDLE_OPCODE(FCONST_2, 0x0d)
  GEEVM_HANDLE_OPCODE(DCONST_0, 0x0e)
  GEEVM_HANDLE_OPCODE(DCONST_1, 0x0f)
  GEEVM_HANDLE_OPCODE(BIPUSH, 0x10)
  GEEVM_HANDLE_OPCODE(SIPUSH, 0x11)
  GEEVM_HANDLE_OPCODE(LDC, 0x12)
  GEEVM_HANDLE_OPCODE(LDC_W, 0x13)
  GEEVM_HANDLE_OPCODE(LDC2_W, 0x14)
  // Loads
  //==-------------------------------------------------------------------==//
  GEEVM_HANDLE_OPCODE(ILOAD, 0x15)
  GEEVM_HANDLE_OPCODE(LLOAD, 0x16)
  GEEVM_HANDLE_OPCODE(FLOAD, 0x17)
  GEEVM_HANDLE_OPCODE(DLOAD, 0x18)
  GEEVM_HANDLE_OPCODE(ALOAD, 0x19)
  GEEVM_HANDLE_OPCODE(ILOAD_0, 0x1a)
  GEEVM_HANDLE_OPCODE(ILOAD_1, 0x1b)
  GEEVM_HANDLE_OPCODE(ILOAD_2, 0x1c)
  GEEVM_HANDLE_OPCODE(ILOAD_3, 0x1d)
  GEEVM_HANDLE_OPCODE(LLOAD_0, 0x1e)
  GEEVM_HANDLE_OPCODE(LLOAD_1, 0x1f)
  GEEVM_HANDLE_OPCODE(LLOAD_2, 0x20)
  GEEVM_HANDLE_OPCODE(LLOAD_3, 0x21)
  GEEVM_HANDLE_OPCODE(FLOAD_0, 0x22)
  GEEVM_HANDLE_OPCODE(FLOAD_1, 0x23)
  GEEVM_HANDLE_OPCODE(FLOAD_2, 0x24)
  GEEVM_HANDLE_OPCODE(FLOAD_3, 0x25)
  GEEVM_HANDLE_OPCODE(DLOAD_0, 0x26)
  GEEVM_HANDLE_OPCODE(DLOAD_1, 0x27)
  GEEVM_HANDLE_OPCODE(DLOAD_2, 0x28)
  GEEVM_HANDLE_OPCODE(DLOAD_3, 0x29)
  GEEVM_HANDLE_OPCODE(ALOAD_0, 0x2a)
  GEEVM_HANDLE_OPCODE(ALOAD_1, 0x2b)
  GEEVM_HANDLE_OPCODE(ALOAD_2, 0x2c)
  GEEVM_HANDLE_OPCODE(ALOAD_3, 0x2d)
  GEEVM_HANDLE_OPCODE(IALOAD, 0x2e)
  GEEVM_HANDLE_OPCODE(LALOAD, 0x2f)
  GEEVM_HANDLE_OPCODE(FALOAD, 0x30)
  GEEVM_HANDLE_OPCODE(DALOAD, 0x31)
  GEEVM_HANDLE_OPCODE(AALOAD, 0x32)
  GEEVM_HANDLE_OPCODE(BALOAD, 0x33)
  GEEVM_HANDLE_OPCODE(CALOAD, 0x34)
  GEEVM_HANDLE_OPCODE(SALOAD, 0x35)
  // Stores
  //==-------------------------------------------------------------------==//
  GEEVM_HANDLE_OPCODE(ISTORE, 0x36)
  GEEVM_HANDLE_OPCODE(LSTORE, 0x37)
  GEEVM_HANDLE_OPCODE(FSTORE, 0x38)
  GEEVM_HANDLE_OPCODE(DSTORE, 0x39)
  GEEVM_HANDLE_OPCODE(ASTORE, 0x3a)
  GEEVM_HANDLE_OPCODE(ISTORE_0, 0x3b)
  GEEVM_HANDLE_OPCODE(ISTORE_1, 0x3c)
  GEEVM_HANDLE_OPCODE(ISTORE_2, 0x3d)
  GEEVM_HANDLE_OPCODE(ISTORE_3, 0x3e)
  GEEVM_HANDLE_OPCODE(LSTORE_0, 0x3f)
  GEEVM_HANDLE_OPCODE(LSTORE_1, 0x40)
  GEEVM_HANDLE_OPCODE(LSTORE_2, 0x41)
  GEEVM_HANDLE_OPCODE(LSTORE_3, 0x42)
  GEEVM_HANDLE_OPCODE(FSTORE_0, 0x43)
  GEEVM_HANDLE_OPCODE(FSTORE_1, 0x44)
  GEEVM_HANDLE_OPCODE(FSTORE_2, 0x45)
  GEEVM_HANDLE_OPCODE(FSTORE_3, 0x46)
  GEEVM_HANDLE_OPCODE(DSTORE_0, 0x47)
  GEEVM_HANDLE_OPCODE(DSTORE_1, 0x48)
  GEEVM_HANDLE_OPCODE(DSTORE_2, 0x49)
  GEEVM_HANDLE_OPCODE(DSTORE_3, 0x4a)
  GEEVM_HANDLE_OPCODE(ASTORE_0, 0x4b)
  GEEVM_HANDLE_OPCODE(ASTORE_1, 0x4c)
  GEEVM_HANDLE_OPCODE(ASTORE_2, 0x4d)
  GEEVM_HANDLE_OPCODE(ASTORE_3, 0x4e)
  GEEVM_HANDLE_OPCODE(IASTORE, 0x4f)
  GEEVM_HANDLE_OPCODE(LASTORE, 0x50)
  GEEVM_HANDLE_OPCODE(FASTORE, 0x51)
  GEEVM_HANDLE_OPCODE(DASTORE, 0x52)
  GEEVM_HANDLE_OPCODE(AASTORE, 0x53)
  GEEVM_HANDLE_OPCODE(BASTORE, 0x54)
  GEEVM_HANDLE_OPCODE(CASTORE, 0x55)
  GEEVM_HANDLE_OPCODE(SASTORE, 0x56)
  // Stack
  //==-------------------------------------------------------------------==//
  GEEVM_HANDLE_OPCODE(POP, 0x57)
  GEEVM_HANDLE_OPCODE(POP2, 0x58)
  GEEVM_HANDLE_OPCODE(DUP, 0x59)
  GEEVM_HANDLE_OPCODE(DUP_X1, 0x5a)
  GEEVM_HANDLE_OPCODE(DUP_X2, 0x5b)
  GEEVM_HANDLE_OPCODE(DUP2, 0x5c)
  GEEVM_HANDLE_OPCODE(DUP2_X1, 0x5d)
  GEEVM_HANDLE_OPCODE(DUP2_X2, 0x5e)
  GEEVM_HANDLE_OPCODE(SWAP, 0x5f)
  // Math
  //==-------------------------------------------------------------------==//
  GEEVM_HANDLE_OPCODE(IADD, 0x60)
  GEEVM_HANDLE_OPCODE(LADD, 0x61)
  GEEVM_HANDLE_OPCODE(FADD, 0x62)
  GEEVM_HANDLE_OPCODE(DADD, 0x63)
  GEEVM_HANDLE_OPCODE(ISUB, 0x64)
  GEEVM_HANDLE_OPCODE(LSUB, 0x65)
  GEEVM_HANDLE_OPCODE(FSUB, 0x66)
  GEEVM_HANDLE_OPCODE(DSUB, 0x67)
  GEEVM_HANDLE_OPCODE(IMUL, 0x68)
  GEEVM_HANDLE_OPCODE(LMUL, 0x69)
  GEEVM_HANDLE_OPCODE(FMUL, 0x6a)
  GEEVM_HANDLE_OPCODE(DMUL, 0x6b)
  GEEVM_HANDLE_OPCODE(IDIV, 0x6c)
  GEEVM_HANDLE_OPCODE(LDIV, 0x6d)
  GEEVM_HANDLE_OPCODE(FDIV, 0x6e)
  GEEVM_HANDLE_OPCODE(DDIV, 0x6f)
  GEEVM_HANDLE_OPCODE(IREM, 0x70)
  GEEVM_HANDLE_OPCODE(LREM, 0x71)
  GEEVM_HANDLE_OPCODE(FREM, 0x72)
  GEEVM_HANDLE_OPCODE(DREM, 0x73)
  GEEVM_HANDLE_OPCODE(INEG, 0x74)
  GEEVM_HANDLE_OPCODE(LNEG, 0x75)
  GEEVM_HANDLE_OPCODE(FNEG, 0x76)
  GEEVM_HANDLE_OPCODE(DNEG, 0x77)
  GEEVM_HANDLE_OPCODE(ISHL, 0x78)
  GEEVM_HANDLE_OPCODE(LSHL, 0x79)
  GEEVM_HANDLE_OPCODE(ISHR, 0x7a)
  GEEVM_HANDLE_OPCODE(LSHR, 0x7b)
  GEEVM_HANDLE_OPCODE(IUSHR, 0x7c)
  GEEVM_HANDLE_OPCODE(LUSHR, 0x7d)
  GEEVM_HANDLE_OPCODE(IAND, 0x7e)
  GEEVM_HANDLE_OPCODE(LAND, 0x7f)
  GEEVM_HANDLE_OPCODE(IOR, 0x80)
  GEEVM_HANDLE_OPCODE(LOR, 0x81)
  GEEVM_HANDLE_OPCODE(IXOR, 0x82)
  GEEVM_HANDLE_OPCODE(LXOR, 0x83)
  GEEVM_HANDLE_OPCODE(IINC, 0x84)
  GEEVM_HANDLE_OPCODE(I2L, 0x85)
  GEEVM_HANDLE_OPCODE(I2F, 0x86)
  GEEVM_HANDLE_OPCODE(I2D, 0x87)
  GEEVM_HANDLE_OPCODE(L2I, 0x88)
  GEEVM_HANDLE_OPCODE(L2F, 0x89)
  GEEVM_HANDLE_OPCODE(L2D, 0x8a)
  GEEVM_HANDLE_OPCODE(F2I, 0x8b)
  GEEVM_HANDLE_OPCODE(F2L, 0x8c)
  GEEVM_HANDLE_OPCODE(F2D, 0x8d)
  GEEVM_HANDLE_OPCODE(D2I, 0x8e)
  GEEVM_HANDLE_OPCODE(D2L, 0x8f)
  GEEVM_HANDLE_OPCODE(D2F, 0x90)
  GEEVM_HANDLE_OPCODE(I2B, 0x91)
  GEEVM_HANDLE_OPCODE(I2C, 0x92)
  GEEVM_HANDLE_OPCODE(I2S, 0x93)
  // Comparisons
  //==-------------------------------------------------------------------==//
  GEEVM_HANDLE_OPCODE(LCMP, 0x94)
  GEEVM_HANDLE_OPCODE(FCMPL, 0x95)
  GEEVM_HANDLE_OPCODE(FCMPG, 0x96)
  GEEVM_HANDLE_OPCODE(DCMPL, 0x97)
  GEEVM_HANDLE_OPCODE(DCMPG, 0x98)
  GEEVM_HANDLE_OPCODE(IFEQ, 0x99)
  GEEVM_HANDLE_OPCODE(IFNE, 0x9a)
  GEEVM_HANDLE_OPCODE(IFLT, 0x9b)
  GEEVM_HANDLE_OPCODE(IFGE, 0x9c)
  GEEVM_HANDLE_OPCODE(IFGT, 0x9d)
  GEEVM_HANDLE_OPCODE(IFLE, 0x9e)
  GEEVM_HANDLE_OPCODE(IF_ICMPEQ, 0x9f)
  GEEVM_HANDLE_OPCODE(IF_ICMPNE, 0xa0)
  GEEVM_HANDLE_OPCODE(IF_ICMPLT, 0xa1)
  GEEVM_HANDLE_OPCODE(IF_ICMPGE, 0xa2)
  GEEVM_HANDLE_OPCODE(IF_ICMPGT, 0xa3)
  GEEVM_HANDLE_OPCODE(IF_ICMPLE, 0xa4)
  GEEVM_HANDLE_OPCODE(IF_ACMPEQ, 0xa5)
  GEEVM_HANDLE_OPCODE(IF_ACMPNE, 0xa6)
  // Control
  //==-------------------------------------------------------------------==//
  GEEVM_HANDLE_OPCODE(GOTO, 0xa7)
  GEEVM_HANDLE_OPCODE(JSR, 0xa8)
  GEEVM_HANDLE_OPCODE(RET, 0xa9)
  GEEVM_HANDLE_OPCODE(TABLESWITCH, 0xaa)
  GEEVM_HANDLE_OPCODE(LOOKUPSWITCH, 0xab)
  GEEVM_HANDLE_OPCODE(IRETURN, 0xac)
  GEEVM_HANDLE_OPCODE(LRETURN, 0xad)
  GEEVM_HANDLE_OPCODE(FRETURN, 0xae)
  GEEVM_HANDLE_OPCODE(DRETURN, 0xaf)
  GEEVM_HANDLE_OPCODE(ARETURN, 0xb0)
  GEEVM_HANDLE_OPCODE(RETURN, 0xb1)
  // References
  //==-------------------------------------------------------------------==//
  GEEVM_HANDLE_OPCODE(GETSTATIC, 0xb2)
  GEEVM_HANDLE_OPCODE(PUTSTATIC, 0xb3)
  GEEVM_HANDLE_OPCODE(GETFIELD, 0xb4)
  GEEVM_HANDLE_OPCODE(PUTFIELD, 0xb5)
  GEEVM_HANDLE_OPCODE(INVOKEVIRTUAL, 0xb6)
  GEEVM_HANDLE_OPCODE(INVOKESPECIAL, 0xb7)
  GEEVM_HANDLE_OPCODE(INVOKESTATIC, 0xb8)
  GEEVM_HANDLE_OPCODE(INVOKEINTERFACE, 0xb9)
  GEEVM_HANDLE_OPCODE(INVOKEDYNAMIC, 0xba)
  GEEVM_HANDLE_OPCODE(NEW, 0xbb)
  GEEVM_HANDLE_OPCODE(NEWARRAY, 0xbc)
  GEEVM_HANDLE_OPCODE(ANEWARRAY, 0xbd)
  GEEVM_HANDLE_OPCODE(ARRAYLENGTH, 0xbe)
  GEEVM_HANDLE_OPCODE(ATHROW, 0xbf)
  GEEVM_HANDLE_OPCODE(CHECKCAST, 0xc0)
  GEEVM_HANDLE_OPCODE(INSTANCEOF, 0xc1)
  GEEVM_HANDLE_OPCODE(MONITORENTER, 0xc2)
  GEEVM_HANDLE_OPCODE(MONITOREXIT, 0xc3)
  // Extended
  //==-------------------------------------------------------------------==//
  GEEVM_HANDLE_OPCODE(WIDE, 0xc4)
  GEEVM_HANDLE_OPCODE(MULTIANEWARRAY, 0xc5)
  GEEVM_HANDLE_OPCODE(IFNULL, 0xc6)
  GEEVM_HANDLE_OPCODE(IFNONNULL, 0xc7)
  GEEVM_HANDLE_OPCODE(GOTO_W, 0xc8)
  GEEVM_HANDLE_OPCODE(JSR_W, 0xc9)
  // Reserved
  //==-------------------------------------------------------------------==//
  GEEVM_HANDLE_OPCODE(BREAKPOINT, 0xca)
  GEEVM_HANDLE_OPCODE(IMPDEP1, 0xfe)
  GEEVM_HANDLE_OPCODE(IMPDEP2, 0xff)
#endif
